{
  "_comment": "Manifest of llama.cpp CUDA tarballs that LMForge can download at init / engine install time. Built by .github/workflows/build-llamacpp-cuda.yml; sha256 values are filled in manually from each release's <tarball>.tar.gz.sha256 companion after the workflow runs (CI publishes the .sha256 file alongside the tarball). Embedded into the lmforge binary via include_str! in src/engine/variant.rs.",
  "llamacpp_tag": "b9351",
  "release_tag": "llamacpp-b9351",
  "variants": [
    {
      "id": "cuda12",
      "cuda": "12.8.1",
      "driver_min": "570.26",
      "cap_min": 7.5,
      "platform": "linux-x64",
      "url": "https://github.com/phoenixtb/lmforge/releases/download/llamacpp-b9351/lmforge-llamacpp-b9351-cuda12-linux-x64.tar.gz",
      "sha256": "<populated-by-ci>"
    },
    {
      "id": "cuda13",
      "cuda": "13.1.0",
      "driver_min": "590.44.01",
      "cap_min": 7.5,
      "platform": "linux-x64",
      "opt_in_only": true,
      "url": "https://github.com/phoenixtb/lmforge/releases/download/llamacpp-b9351/lmforge-llamacpp-b9351-cuda13-linux-x64.tar.gz",
      "sha256": "<populated-by-ci>"
    }
  ]
}
